Workbook

Sheet Cover_Page
F1: NEULAND LABORATORIES LTD.
F2: Equity Research & Valuation Report
B5: Contents: | F5: Project Information | I5: Key Metrics | J5: FY25
B6: 1. Company Overview | F6: Company | G6: Neuland Laboratories | I6: Market Cap | J6: ₹21,842 Cr
B7: 2. Industry Analysis | F7: Industry | G7: Pharmaceuticals | I7: ROCE | J7: 0.266
B8: 3. Historical Financials | F8: Methodology | G8: DCF + Comparable Valuation | I8: ROE | J8: 0.17
B9: 4. Ratio Analysis | F9: Valuation date | G9: 46174 | I9: Revenue | J9: ₹1,477 Cr
B10: 5. Investment Thesis | F10: Period Analyzed | G10: FY21–FY25
B11: 6. Forecasts | F11: Prepared By | G11: Aasti Priya
B12: 7. DCF Valuation
B13: 8. Comparable Valuation
B14: 9. Sensitivity Analysis
B15: 10. Final Recommendation
B18: This report is prepared solely for educational and research purposes and does not constitute investment advice.

Sheet Company_Overview
B2: COMPANY SNAPSHOT | E2: REVENUE MIX FY25
B4: Company Name | C4: Neuland Laboratories Ltd. | E4: Segment | F4: Revenue Contribution FY25
B5: Founded | C5: 1984 | E5: CDMO | F5: 0.43
B6: Headquarterd in | C6: Hyderabad, India | E6: Prime APIs | F6: 0.33
B7: Employees | C7: ~2,100 | E7: Specialty APIs | F7: 0.18
B8: Industry | C8: Pharmaceuticals | E8: Others | F8: 0.06
B9: Business Model | C9: API & CDMO
B10: Market Cap | C10: ₹21,842 Cr
B11: Current Share Price | C11: 17016
B13: BUSINESS SEGMENTS | E13: INVESTMENT HIGHLIGHTS
E14: *Strong exposure to high-growth API and CDMO segments. *Benefits from China+1 outsourcing trend. *Peptide capacity expansion provides long-term growth potential. *ROCE of 26.6% demonstrates efficient capital allocation. *Long-term growth supported by increasing pharma outsourcing.
B15: Segment | C15: Description
B16: Generic APIs | C16: Established pharmaceutical ingredients
B17: Specialty APIs | C17: High-value complex APIs
B18: CDMO | C18: Contract development & manufacturing services
B20: BUSINESS MODEL FLOWCHART
B27: Key Takeaway: Neuland Laboratories is a specialized API and CDMO manufacturer positioned to benefit from pharmaceutical outsourcing, peptide manufacturing expansion, and the China+1 supply chain diversification trend.

Sheet Industry_Analysis
B2: INDUSTRY OVERVIEW | M2: GROWTH DRIVERS
B3: Pharma Industry: India is one of the world's largest pharmaceutical producers by volume and a major supplier of generic medicines globally. API Industry: APIs are the key active ingredients in drugs. Increasing global demand and supply-chain diversification are creating growth opportunities for Indian API manufacturers. CDMO Industry: CDMOs provide outsourced drug development and manufacturing services. The sector is growing as pharmaceutical companies focus on R&D while outsourcing production. | M3: China+1: Global pharma companies are diversifying sourcing away from China, benefiting Indian manufacturers. Outsourcing: Drug companies increasingly outsource manufacturing to reduce costs and improve efficiency. Innovation in Drugs: Growth in complex molecules and specialty drugs increases demand for advanced manufacturing capabilities. Peptides: Rising demand for peptide-based therapies supports long-term industry growth.
B10: COMPETITIVE ADVANTAGE OF INDIA
B11: Cost Advantage: Lower manufacturing costs compared with developed markets. Skilled Workforce: Large pool of scientists, engineers, and pharmaceutical professionals. Regulatory Compliance: Strong presence of USFDA and EU-approved facilities.
M12: INDUSTRY OUTLOOK
M13: The Indian API and CDMO industries are expected to benefit from increasing pharmaceutical outsourcing, China+1 diversification, and growing demand for complex molecules and peptide-based therapies. These trends support long-term growth opportunities for companies such as Neuland Laboratories. • India supplies ~20% of the world's generic medicines by volume. • The Indian pharmaceutical industry is expected to continue benefiting from outsourcing and China+1 diversification trends.
B15: RISKS
B16: Regulatory: Compliance failures can result in warning letters or import restrictions. Geopolitical: Trade disruptions and policy changes may affect exports. Supply Chain: Dependence on imported raw materials can impact production. Quality Issues: Product recalls or manufacturing failures can damage reputation.

Sheet Historical_Financials
B2: INCOME STATEMENT | D2: All figures in ₹ Crore unless otherwise stated
B3: Year | C3: FY22 | D3: FY23 | E3: FY24 | F3: FY25 | G3: FY26
B4: Revenue | C4: 951 | D4: 1191 | E4: 1559 | F4: 1477 | G4: 2023
B5: Operating Profit | C5: 144 | D5: 273 | E5: 463 | F5: 331 | G5: 574
B6: Net Profit | C6: 64 | D6: 164 | E6: 300 | F6: 260 | G6: 364
B7: EPS | C7: 49.74 | D7: 127.45 | E7: 233.89 | F7: 202.74 | G7: 283.71
B9: CASH FLOW STATEMENT
B10: Year | C10: FY22 | D10: FY23 | E10: FY24 | F10: FY25 | G10: FY26
B11: CFO (Operating Cash Flow) | C11: 60 | D11: 237 | E11: 261 | F11: 317 | G11: 347
B12: Capex | C12: -98 | D12: -66 | E12: -144 | F12: -206 | G12: -397
B13: Free Cash Flow | C13: =SUM(C12,C11) -> -38 | D13: =SUM(D12,D11) -> 171 | E13: =SUM(E12,E11) -> 117 | F13: =SUM(F12,F11) -> 111 | G13: =SUM(G12,G11) -> -50
B15: BALANCE SHEET
B16: Year | C16: FY22 | D16: FY23 | E16: FY24 | F16: FY25 | G16: FY26 | I16: Key Insight: Revenue grew from ₹951 Cr in FY22 to ₹2,023 Cr in FY26, while net profit increased from ₹64 Cr to ₹364 Cr. Despite fluctuations in certain years, Neuland demonstrated strong profitability, expanding scale, and a healthy financial position over the period.
B17: Total Assets | C17: 1383 | D17: 1580 | E17: 1833 | F17: 2180 | G17: 2930
B18: Borrowings | C18: 241 | D18: 128 | E18: 95 | F18: 157 | G18: 301
B19: Shareholders' Equity | C19: 841 | D19: 994 | E19: 1283 | F19: 1525 | G19: 1875
B20: Cash & Equivalents | C20: 20 | D20: 59 | E20: 117 | F20: 259 | G20: 355
B22: Data Source: Historical financial data extracted from Screener.in and cross-verified with annual reports where required.
B23: Figures in ₹ Crore.
B25: Financial Performance Summary
B26: • Revenue more than doubled from ₹951 Cr in FY22 to ₹2,023 Cr in FY26. • Operating profit increased from ₹144 Cr to ₹574 Cr, reflecting improved operating efficiency and scale benefits. • Net profit grew from ₹64 Cr in FY22 to ₹364 Cr in FY26, driven by stronger margins and business expansion. • Total assets expanded from ₹1,383 Cr to ₹2,930 Cr, supporting future manufacturing and capacity growth. • The company maintained a healthy balance sheet with debt-to-equity below 0.20x and cash reserves increasing to ₹355 Cr in FY26.

Sheet Ratio_Analysis
B2: Year | C2: FY22 | D2: FY23 | E2: FY24 | F2: FY25 | G2: FY26 | I2: Ratio Analysis Summary
B3: Growth | I3: Profitability: Operating margin improved from 15% in FY22 to 28% in FY26, while net profit margin expanded from 7% to 18%, reflecting stronger operational efficiency and scale. Leverage: Debt-to-equity remained below 0.30x throughout the period, indicating a conservative balance sheet and manageable financial risk. Efficiency: Total assets grew from ₹1,383 Cr in FY22 to ₹2,930 Cr in FY26, supporting capacity expansion and future growth initiatives. Returns: ROE improved from 8% to 19%, while ROA increased from 5% to 12%, demonstrating improved capital allocation and profitability.
B4: Revenue Growth % | C4: - | D4: =(Historical_Financials!D4-Historical_Financials!C4)/Historical_Financials!C4 -> 0.25236593 | E4: =(Historical_Financials!E4-Historical_Financials!D4)/Historical_Financials!D4 -> 0.30898405 | F4: =(Historical_Financials!F4-Historical_Financials!E4)/Historical_Financials!E4 -> -0.052597819 | G4: =(Historical_Financials!G4-Historical_Financials!F4)/Historical_Financials!F4 -> 0.36966825
B5: Net Profit growth | C5: - | D5: =(Historical_Financials!D6-Historical_Financials!C6)/Historical_Financials!C6 -> 1.5625 | E5: =(Historical_Financials!E6-Historical_Financials!D6)/Historical_Financials!D6 -> 0.82926829 | F5: =(Historical_Financials!F6-Historical_Financials!E6)/Historical_Financials!E6 -> -0.13333333 | G5: =(Historical_Financials!G6-Historical_Financials!F6)/Historical_Financials!F6 -> 0.4
B7: Margin
B8: Operating Margin% | C8: =Historical_Financials!C5/Historical_Financials!C4 -> 0.15141956 | D8: =Historical_Financials!D5/Historical_Financials!D4 -> 0.22921914 | E8: =Historical_Financials!E5/Historical_Financials!E4 -> 0.29698525 | F8: =Historical_Financials!F5/Historical_Financials!F4 -> 0.22410291 | G8: =Historical_Financials!G5/Historical_Financials!G4 -> 0.28373702
B9: Net Profit Margin% | C9: =Historical_Financials!C6/Historical_Financials!C4 -> 0.067297581 | D9: =Historical_Financials!D6/Historical_Financials!D4 -> 0.13769941 | E9: =Historical_Financials!E6/Historical_Financials!E4 -> 0.19243105 | F9: =Historical_Financials!F6/Historical_Financials!F4 -> 0.1760325 | G9: =Historical_Financials!G6/Historical_Financials!G4 -> 0.1799308
B11: Leverage
B12: Debt-to-equity | C12: =Historical_Financials!C18/Historical_Financials!C19 -> 0.28656361 | D12: =Historical_Financials!D18/Historical_Financials!D19 -> 0.12877264 | E12: =Historical_Financials!E18/Historical_Financials!E19 -> 0.074045207 | F12: =Historical_Financials!F18/Historical_Financials!F19 -> 0.10295082 | G12: =Historical_Financials!G18/Historical_Financials!G19 -> 0.16053333
B14: Asset Efficiency
B15: Asset Growth | C15: - | D15: =(Historical_Financials!D17-Historical_Financials!C17)/Historical_Financials!C17 -> 0.14244396 | E15: =(Historical_Financials!E17-Historical_Financials!D17)/Historical_Financials!D17 -> 0.16012658 | F15: =(Historical_Financials!F17-Historical_Financials!E17)/Historical_Financials!E17 -> 0.18930715 | G15: =(Historical_Financials!G17-Historical_Financials!F17)/Historical_Financials!F17 -> 0.3440367
B17: Return Ratios
B18: ROE | C18: =Historical_Financials!C6/Historical_Financials!C19 -> 0.076099881 | D18: =Historical_Financials!D6/Historical_Financials!D19 -> 0.16498994 | E18: =Historical_Financials!E6/Historical_Financials!E19 -> 0.23382697 | F18: =Historical_Financials!F6/Historical_Financials!F19 -> 0.1704918 | G18: =Historical_Financials!G6/Historical_Financials!G19 -> 0.19413333
B19: ROA | C19: =Historical_Financials!C6/Historical_Financials!C17 -> 0.046276211 | D19: =Historical_Financials!D6/Historical_Financials!D17 -> 0.10379747 | E19: =Historical_Financials!E6/Historical_Financials!E17 -> 0.16366612 | F19: =Historical_Financials!F6/Historical_Financials!F17 -> 0.11926606 | G19: =Historical_Financials!G6/Historical_Financials!G17 -> 0.12423208

Sheet Comparable_Valuation
B2: Company | C2: Market Cap (₹ Cr) | D2: P/E | E2: ROE (%) | F2: ROCE (%) | G2: Revenue Growth (%) | H2: Comments
B3: Neuland Labs | C3: =DCF!M4 -> 21842 | D3: 60.2 | E3: =Ratio_Analysis!G18 -> 0.19413333 | F3: 26.6 | G3: =Ratio_Analysis!G4 -> 0.36966825 | H3: Strong ROCE, healthy profitability, and sharp revenue recovery in FY26.
B4: Divi's Labs | C4: 176558 | D4: 67.3 | E4: 0.165 | F4: 22 | G4: 0.1931 | H4: Industry leader with consistent growth.
B5: Syngene | C5: 17,715 | D5: 47.2 | E5: 7.86 % | F5: 10.1 | G5: 0.0441 | H5: Lower profitability but strong CDMO exposure.
B6: Laurus Labs | C6: 73,363 | D6: 82 | E6: 18.3 % | F6: 17.8 | G6: 0.1018 | H6: Higher growth potential but more volatile.
B7: Torrent Pharma | C7: 150104 | D7: 68.64 | E7: 27.4 % | F7: 15.2 | G7: 0.0735 | H7: Diversified pharma player with strong ROE.
B8: Peer Average | C8: =AVERAGE(C3:C7) -> 116168 | D8: =AVERAGE(D3:D7) -> 65.068 | E8: =AVERAGE(E3:E7) -> 0.17956667 | F8: =AVERAGE(F3:F7) -> 21.266667 | G8: =AVERAGE(G3:G7) -> 0.15643365
B10: Comparable Valuation Summary
B11: Neuland Laboratories trades at a lower valuation than certain premium peers such as Divi's Labs while delivering superior ROCE and competitive return ratios. The company demonstrated a strong recovery in FY26 with revenue growth of 37% and ROE of 19%. Compared with peers, Neuland combines healthy profitability, efficient capital allocation, and exposure to long-term API and CDMO growth opportunities.

Sheet DCF
B2: Assumption | C2: FY27 | D2: FY28 | E2: FY29 | F2: FY30 | G2: FY31 | I2: Assumption | J2: Value | L2: Market Data | M2: Value
B3: Revenue Growth | C3: 0.15 | D3: 0.13 | E3: 0.11 | F3: 0.1 | G3: 0.08 | I3: Tax Rate | J3: 0.25 | L3: Current Share Price (₹) | M3: 17016
B4: Operating Margin | C4: 0.27 | D4: 0.27 | E4: 0.28 | F4: 0.28 | G4: 0.28 | I4: Discount Rate | J4: 0.12 | L4: Market Capitalization (₹ Cr) | M4: 21842
I5: Terminal Growth Rate | J5: 0.04
B6: Year | C6: FY27 | D6: FY28 | E6: FY29 | F6: FY30 | G6: FY31
B7: Revenue | C7: =Historical_Financials!G4*(1+DCF!C3) -> 2326.45 | D7: =C7*(1+D3) -> 2628.8885 | E7: =D7*(1+E3) -> 2918.0662 | F7: =E7*(1+F3) -> 3209.8729 | G7: =F7*(1+G3) -> 3466.6627 | I7: DCF Summary | J7: Value
B8: Operating Profit | C8: =C7*C4 -> 628.1415 | D8: =D7*D4 -> 709.79989 | E8: =E7*E4 -> 817.05855 | F8: =F7*F4 -> 898.7644 | G8: =G7*G4 -> 970.66555 | I8: PV of Forecast Cash Flows | J8: =SUM(C16:G16) -> 2122.6632
B9: Tax | C9: 0.25 | D9: 0.25 | E9: 0.25 | F9: 0.25 | G9: 0.25 | I9: PV of Terminal Value | J9: =C21 -> 5370.1216
B10: After-Tax Operating Profit | C10: =C8*(1-C9) -> 471.10612 | D10: =D8*(1-D9) -> 532.34992 | E10: =E8*(1-E9) -> 612.79391 | F10: =F8*(1-F9) -> 674.0733 | G10: =G8*(1-G9) -> 727.99916 | I10: Enterprise Value | J10: =SUM(J8:J9) -> 7492.7848
B11: Free Cash Flow | C11: =C10 -> 471.10612 | D11: =D10 -> 532.34992 | E11: =E10 -> 612.79391 | F11: =F10 -> 674.0733 | G11: =G10 -> 727.99916 | I11: Add: Cash | J11: =Historical_Financials!G20 -> 355
I12: Less: Debt | J12: =Historical_Financials!G18 -> 301
B13: Year | C13: FY27 | D13: FY28 | E13: FY29 | F13: FY30 | G13: FY31 | I13: Equity Value | J13: =J10+J11-J12 -> 7546.7848
B14: Free Cash Flow | C14: =C11 -> 471.10612 | D14: =D11 -> 532.34992 | E14: =E11 -> 612.79391 | F14: =F11 -> 674.0733 | G14: =G11 -> 727.99916 | I14: Shares Outstanding (Cr) | J14: =M4/M3 -> 1.2836154
B15: Discount Factor | C15: =1/(1+$J$4)^1 -> 0.89285714 | D15: =1/(1+$J$4)^2 -> 0.79719388 | E15: =1/(1+$J$4)^3 -> 0.71178025 | F15: =1/(1+$J$4)^4 -> 0.63551808 | G15: =1/(1+$J$4)^5 -> 0.56742686 | I15: Intrinsic Value Per Share (₹) | J15: =J13/J14 -> 5879.3192
B16: Present Value | C16: =C14*C15 -> 420.63047 | D16: =D14*D15 -> 424.3861 | E16: =E14*E15 -> 436.1746 | F16: =F14*F15 -> 428.38577 | G16: =G14*G15 -> 413.08628
B18: Terminal Value Calculation | C18: Value | E18: DCF Conclusion: Based on projected cash flows, a 12% discount rate, and a 4% terminal growth rate, the estimated intrinsic value is ₹5,879 per share. The valuation is below the current market price of ₹17,016, suggesting that investors may be pricing in stronger long-term growth expectations than those reflected in the base-case assumptions.
B19: FCF FY31 | C19: =G14*(1+J5) -> 757.11913
B20: Terminal Value | C20: =C19/(J4-J5) -> 9463.9891
B21: PV of Terminal Value | C21: =C20*G15 -> 5370.1216

Sheet Sensitivity
B2: Assumption | C2: Bear | D2: Base | E2: Bull | H2: Assumption | I2: FY27 | J2: FY28 | K2: FY29 | L2: FY30 | M2: FY31
B3: FY27 Growth | C3: 0.1 | D3: 0.15 | E3: 0.2 | G3: Bear Case | H3: Revenue Growth | I3: 0.1 | J3: 0.08 | K3: 0.07 | L3: 0.06 | M3: 0.05
B4: FY28 Growth | C4: 0.08 | D4: 0.13 | E4: 0.18 | H4: Operating Margin | I4: 0.24 | J4: 0.23 | K4: 0.22 | L4: 0.22 | M4: 0.21
B5: FY29 Growth | C5: 0.07 | D5: 0.11 | E5: 0.16 | G5: Base Case | H5: Revenue Growth | I5: 0.15 | J5: 0.13 | K5: 0.11 | L5: 0.1 | M5: 0.08
B6: FY30 Growth | C6: 0.06 | D6: 0.1 | E6: 0.14 | H6: Operating Margin | I6: 0.27 | J6: 0.27 | K6: 0.28 | L6: 0.28 | M6: 0.28
B7: FY31 Growth | C7: 0.05 | D7: 0.08 | E7: 0.12 | G7: Bull Case | H7: Revenue Growth | I7: 0.2 | J7: 0.18 | K7: 0.16 | L7: 0.14 | M7: 0.12
B8: Terminal Growth | C8: 0.03 | D8: 0.04 | E8: 0.05 | H8: Operating Margin | I8: 0.29 | J8: 0.3 | K8: 0.3 | L8: 0.31 | M8: 0.32
B9: Discount Rate | C9: 0.13 | D9: 0.12 | E9: 0.1
B10: Intrinsic Value | C10: 3950 | D10: =DCF!J15 -> 5879.3192 | E10: 8420
B11: Current Price | C11: 17016 | D11: 17016 | E11: 17016
B12: Upside/(Downside) | C12: =(C10/C11)-1 -> -0.76786554 | D12: =(D10/D11)-1 -> -0.65448289 | E12: =(E10/E11)-1 -> -0.5051716
B14: Sensitivity Analysis Conclusion
B15: The valuation outcome is highly sensitive to assumptions regarding revenue growth, operating margins, discount rates, and terminal growth. Under the base-case assumptions, the estimated intrinsic value is ₹5,879 per share. The bear and bull scenarios demonstrate the range of possible outcomes under varying business performance and market conditions. While the DCF valuation remains below the current market price across all scenarios, the market may be pricing in stronger long-term growth expectations from Neuland's API and CDMO businesses, future capacity expansion, and peptide manufacturing opportunities.

Sheet Investment_Thesis
B2: Business Overview
B4: Neuland Laboratories is an API and CDMO-focused pharmaceutical company serving global pharmaceutical and biotechnology customers.
B6: Key Strengths
B7: Strong position in API and CDMO segments. Beneficiary of China+1 outsourcing trend. Expanding peptide manufacturing capabilities. Strong ROCE of 26.6% and improving profitability. Healthy balance sheet with low leverage. Revenue recovered strongly in FY26.
B15: Key Risks
B16: Premium market valuation relative to intrinsic value estimates. Dependence on customer demand cycles and project execution. Regulatory and compliance risks in global markets. Margin pressure from raw material cost fluctuations. Execution risk related to capacity expansion.
B23: Preliminary View
B24: Neuland Laboratories appears to be a fundamentally strong pharmaceutical company with attractive exposure to the API and CDMO segments. The company delivered a strong recovery in FY26, supported by improving profitability and expanding manufacturing capabilities. While the current market valuation remains demanding relative to the base-case DCF estimate, long-term growth opportunities from outsourcing trends, peptide manufacturing, and capacity expansion continue to support the investment case.

Sheet Final Recommendation
B2: Valuation Summary
B3: Metric | C3: Value
B4: Current Market Price | C4: 17016
B5: DCF Intrinsic Value | C5: 5879
B6: Bear Case Value | C6: 3950
B7: Bull Case Value | C7: 8420
B9: Recommendation
B10: Neuland Laboratories demonstrates strong business fundamentals, high capital efficiency, and attractive industry positioning. Although the DCF valuation indicates a value below the current market price, the company remains well positioned to benefit from long-term growth in pharmaceutical outsourcing and specialty manufacturing. Investors appear to be assigning a premium valuation based on future growth expectations.
B16: Disclaimer
B17: This report is prepared solely for educational and research purposes and should not be considered investment advice.
